dictionaries.py
dictionaries-0.0.1.dist-info/DESCRIPTION.rst
dictionaries-0.0.1.dist-info/METADATA
dictionaries-0.0.1.dist-info/RECORD
dictionaries-0.0.1.dist-info/WHEEL
dictionaries-0.0.1.dist-info/metadata.json
dictionaries-0.0.1.dist-info/top_level.txt
