Metadata-Version: 1.1
Name: dictionaries
Version: 0.0.1
Summary: Dict implementations with attribute access: ReadonlyDictProxy, FrozenDict, FrozenOrderedDict, Dict, OrderedDict
Home-page: https://github.com/pasztorpisti/py-dictionaries
Author: István Pásztor
Author-email: pasztorpisti@gmail.com
License: MIT
Keywords: Dict FrozenDict FrozenOrderedDict ReadonlyDictProxy ordered readonly frozen proxy attribute access
Platform: UNKNOWN
Classifier: License :: OSI Approved :: MIT License
Classifier: Development Status :: 5 - Production/Stable
Classifier: Intended Audience :: Developers
Classifier: Topic :: Software Development :: Libraries :: Python Modules
Classifier: Programming Language :: Python :: 2
Classifier: Programming Language :: Python :: 3
Classifier: Programming Language :: Python :: Implementation :: CPython
Classifier: Programming Language :: Python :: Implementation :: PyPy
